common_ml-0.0.12.dist-info/DESCRIPTION.rst
common_ml-0.0.12.dist-info/METADATA
common_ml-0.0.12.dist-info/RECORD
common_ml-0.0.12.dist-info/WHEEL
common_ml-0.0.12.dist-info/metadata.json
common_ml-0.0.12.dist-info/top_level.txt
commonml/__init__.py
commonml/version.py
commonml/elasticsearch/__init__.py
commonml/elasticsearch/es_analyzer.py
commonml/elasticsearch/es_reader.py
commonml/elasticsearch/reindex.py
commonml/runner/__init__.py
commonml/runner/runner.py
commonml/skchainer/__init__.py
commonml/skchainer/classifier.py
commonml/skchainer/estimator.py
commonml/skchainer/regressor.py
commonml/skchainer/xy_dataset.py
commonml/text/__init__.py
commonml/text/custom_dict_vectorizer.py
commonml/text/text_to_image.py
commonml/text/vocabulary_transformer.py
commonml/utils/__init__.py
